{
  "shopName": "German Doner",
  "currency": "IQD",
  "categories": [
    {
      "id": "doner",
      "name": "Doner Kebab",
      "items": [
        {
          "id": "doner-kebap-beef",
          "name": "Doner Kebap Beef",
          "description": "Classic beef doner kebap in fresh bread.",
          "price": 5500,
          "image": "https://images.unsplash.com/photo-1618160702438-9b02ab6515c9?w=400&h=300&fit=crop"
        },
        {
          "id": "doner-kebap-chicken",
          "name": "Doner Kebap Chicken",
          "description": "Classic chicken doner kebap in fresh bread.",
          "price": 4500,
          "image": "https://images.unsplash.com/photo-1618160702438-9b02ab6515c9?w=400&h=300&fit=crop"
        },
        {
          "id": "yufka-kebap-beef",
          "name": "Yufka Kebap Beef",
          "description": "Yufka wrap with beef doner meat and salad.",
          "price": 6000,
          "image": "https://images.unsplash.com/photo-1466721591366-2d5fba72006d?w=400&h=300&fit=crop"
        },
        {
          "id": "yufka-kebap-chicken",
          "name": "Yufka Kebap Chicken",
          "description": "Yufka wrap with chicken doner meat and salad.",
          "price": 5000,
          "image": "https://images.unsplash.com/photo-1466721591366-2d5fba72006d?w=400&h=300&fit=crop"
        },
        {
          "id": "kebap-plate-beef",
          "name": "Kebap Plate Beef",
          "description": "Beef doner kebap served on a plate with sides.",
          "price": 11000,
          "image": "https://images.unsplash.com/photo-1582562124811-c09040d0a901?w=400&h=300&fit=crop"
        },
        {
          "id": "kebap-plate-chicken",
          "name": "Kebap Plate Chicken",
          "description": "Chicken doner kebap served on a plate with sides.",
          "price": 10000,
          "image": "https://images.unsplash.com/photo-1582562124811-c09040d0a901?w=400&h=300&fit=crop"
        },
        {
          "id": "lahmacun",
          "name": "Lahmacun",
          "description": "Turkish flatbread with spiced meat topping.",
          "price": 9000,
          "image": "https://images.unsplash.com/photo-1721322800607-8c38375eef04?w=400&h=300&fit=crop"
        },
        {
          "id": "lahmacun-plate",
          "name": "Lahmacun Plate",
          "description": "Lahmacun served with salad and sides.",
          "price": 11000,
          "image": "https://images.unsplash.com/photo-1618160702438-9b02ab6515c9?w=400&h=300&fit=crop"
        }
      ]
    },
    {
      "id": "salads",
      "name": "Fresh Salads",
      "items": [
        {
          "id": "caesar-salad",
          "name": "Caesar Salad",
          "description": "Classic Caesar salad with lettuce, croutons, and parmesan.",
          "price": 6000,
          "image": "https://images.unsplash.com/photo-1504674900247-0877df9cc836?w=400&h=300&fit=crop"
        },
        {
          "id": "greek-salad",
          "name": "Greek Salad",
          "description": "Fresh Greek salad with feta, olives, and vegetables.",
          "price": 7500,
          "image": "https://images.unsplash.com/photo-1519864600265-abb23847ef2c?w=400&h=300&fit=crop"
        }
      ]
    },
    {
      "id": "pide",
      "name": "Pide",
      "items": [
        {
          "id": "sucuk-pide",
          "name": "Sucuk Pide",
          "description": "Turkish flatbread with spicy sausage.",
          "price": 12000,
          "image": "https://images.unsplash.com/photo-1504674900247-0877df9cc836?w=400&h=300&fit=crop"
        },
        {
          "id": "cheese-pide",
          "name": "Cheese Pide",
          "description": "Turkish flatbread with cheese filling.",
          "price": 10000,
          "image": "https://images.unsplash.com/photo-1519864600265-abb23847ef2c?w=400&h=300&fit=crop"
        },
        {
          "id": "doner-pide",
          "name": "Doner Pide",
          "description": "Pide stuffed with doner meat.",
          "price": 10000,
          "image": "https://images.unsplash.com/photo-1464306076886-debca5e8a6b0?w=400&h=300&fit=crop"
        },
        {
          "id": "special-pide",
          "name": "Special Pide",
          "description": "Chef's special Turkish pide.",
          "price": 13000,
          "image": "https://images.unsplash.com/photo-1502741338009-cac2772e18bc?w=400&h=300&fit=crop"
        }
      ]
    },
    {
      "id": "pizza",
      "name": "Pizza",
      "items": [
        {
          "id": "margherita-pizza",
          "name": "Margherita Pizza",
          "description": "Classic pizza with tomato sauce, mozzarella, and basil.",
          "price": 9000,
          "image": "https://images.unsplash.com/photo-1504674900247-0877df9cc836?w=400&h=300&fit=crop"
        },
        {
          "id": "pepperoni-pizza",
          "name": "Pepperoni Pizza",
          "description": "Pizza topped with pepperoni and cheese.",
          "price": 11000,
          "image": "https://images.unsplash.com/photo-1519864600265-abb23847ef2c?w=400&h=300&fit=crop"
        },
        {
          "id": "chicken-pizza",
          "name": "Chicken Pizza",
          "description": "Pizza with grilled chicken, cheese, and vegetables.",
          "price": 11000,
          "image": "https://images.unsplash.com/photo-1464306076886-debca5e8a6b0?w=400&h=300&fit=crop"
        },
        {
          "id": "vegetarian-pizza",
          "name": "Vegetarian Pizza",
          "description": "Pizza with assorted fresh vegetables and cheese.",
          "price": 10000,
          "image": "https://images.unsplash.com/photo-1502741338009-cac2772e18bc?w=400&h=300&fit=crop"
        }
      ]
    },
    {
      "id": "kids-meal",
      "name": "Kids Meal",
      "items": [
        {
          "id": "kids-nugget",
          "name": "Nugget",
          "description": "Chicken nuggets for kids.",
          "price": 5000,
          "image": "https://images.unsplash.com/photo-1504674900247-0877df9cc836?w=400&h=300&fit=crop"
        },
        {
          "id": "kids-fries",
          "name": "Fries",
          "description": "Crispy fries for kids.",
          "price": 3500,
          "image": "https://images.unsplash.com/photo-1582562124811-c09040d0a901?w=400&h=300&fit=crop"
        }
      ]
    },
    {
      "id": "rizzo",
      "name": "Rizzo",
      "items": [
        {
          "id": "rizzo-item",
          "name": "Rizzo",
          "description": "Crispy chicken and rice bowl.",
          "price": 6500,
          "image": "https://images.unsplash.com/photo-1502741338009-cac2772e18bc?w=400&h=300&fit=crop"
        }
      ]
    },
    {
      "id": "drinks",
      "name": "Beverages",
      "items": [
        { "id": "cola", "name": "Cola", "description": "Refreshing cola drink.", "price": 1000, "image": "https://images.unsplash.com/photo-1466721591366-2d5fba72006d?w=400&h=300&fit=crop" },
        { "id": "fanta", "name": "Fanta", "description": "Orange flavored soda.", "price": 1000, "image": "https://images.unsplash.com/photo-1504674900247-0877df9cc836?w=400&h=300&fit=crop" },
        { "id": "water", "name": "Water", "description": "Bottled water.", "price": 1000, "image": "https://images.unsplash.com/photo-1519864600265-abb23847ef2c?w=400&h=300&fit=crop" },
        { "id": "sprite", "name": "Sprite", "description": "Lemon-lime soda.", "price": 1000, "image": "https://images.unsplash.com/photo-1582562124811-c09040d0a901?w=400&h=300&fit=crop" },
        { "id": "cola-diet", "name": "Cola Diet", "description": "Diet cola drink.", "price": 1000, "image": "https://images.unsplash.com/photo-1464306076886-debca5e8a6b0?w=400&h=300&fit=crop" },
        { "id": "yogurt", "name": "Yogurt", "description": "Yogurt drink.", "price": 1500, "image": "https://images.unsplash.com/photo-1502741338009-cac2772e18bc?w=400&h=300&fit=crop" },
        { "id": "soda", "name": "Soda", "description": "Sparkling soda water.", "price": 1000, "image": "https://images.unsplash.com/photo-1582562124811-c09040d0a901?w=400&h=300&fit=crop" },
        { "id": "tea", "name": "Tea", "description": "Hot black tea.", "price": 1000, "image": "https://images.unsplash.com/photo-1721322800607-8c38375eef04?w=400&h=300&fit=crop" }
      ]
    }
  ]
}